flyermlops/__init__.py
flyermlops/cookie_template.zip
flyermlops/exceptions.py
flyermlops/utils.py
flyermlops/data/__init__.py
flyermlops/data/connector.py
flyermlops/data/connector_base.py
flyermlops/data/data_utils.py
flyermlops/drift/__init__.py
flyermlops/drift/data_drift_utils.py
flyermlops/ml_pipelines/__init__.py
flyermlops/ml_pipelines/cli_utils.py
flyermlops/ml_pipelines/flight_builder.py
flyermlops/ml_pipelines/flight_plans.py
flyermlops/ml_pipelines/flight_utils.py
flyermlops/tracking/__init__.py
flyermlops/tracking/data.py
flyermlops/tracking/tracking_objects.py
flyermlops/tracking/tracking_utils.py
flyermlops/tracking/base/__init__.py
flyermlops/tracking/base/params.py
flyermlops/tracking/base/sql_base.py
flyermlops/tracking/base/tracking_base.py
flyermlops-0.0.40.dist-info/LICENSE
flyermlops-0.0.40.dist-info/METADATA
flyermlops-0.0.40.dist-info/WHEEL
flyermlops-0.0.40.dist-info/top_level.txt
flyermlops-0.0.40.dist-info/RECORD
