Metadata-Version: 2.1
Name: flyermlops
Version: 0.0.40
Summary: Helper package for deploying sagemaker pipelines on AWS and MLOPs
Home-page: https://git.delta.com/ods/machine-learning/flyermlops
Author: Steven Forrester
Author-email: steven.forrester@delta.com
License: MIT
Platform: UNKNOWN
Classifier: License :: OSI Approved :: MIT License
Classifier: Programming Language :: Python :: 3
Classifier: Programming Language :: Python :: 3.7
Classifier: Programming Language :: Python :: 3.8
Classifier: Programming Language :: Python :: 3.9
License-File: LICENSE
Requires-Dist: awswrangler (>=2.10.0)
Requires-Dist: pandas (>=1.1.5)
Requires-Dist: psycopg2-binary (>=2.7.7)
Requires-Dist: SQLAlchemy (>=1.4.23)
Requires-Dist: teradatasql (>=17.10.0.2)
Requires-Dist: cookiecutter (>=1.7.3)
Requires-Dist: PyYAML (>=5.3.1)
Requires-Dist: boto3 (>=1.18.64)
Requires-Dist: sagemaker (>=2.63.1)
Requires-Dist: scikit-learn (>=0.24.0)
Requires-Dist: joblib (>=1.1.0)
